{
  "name" : "0205sfd",
  "variables" : [ {
    "name" : "TIME_STEP",
    "equation" : "1",
    "unit" : "Year"
  }, {
    "name" : "INITIAL_TIME",
    "equation" : "2014",
    "unit" : "Year"
  }, {
    "name" : "FINAL_TIME",
    "equation" : "2030",
    "unit" : "Year"
  } ],
  "views" : [ {
    "name" : "View 1",
    "elements" : [ {
      "name" : "online students",
      "type" : "aux",
      "x" : 586.0,
      "y" : 241.0
    }, {
      "name" : "_0",
      "type" : "flow",
      "x" : 459.0,
      "y" : 232.0
    }, {
      "name" : "enrollments",
      "type" : "aux",
      "x" : 459.0,
      "y" : 251.0
    }, {
      "name" : "_0",
      "type" : "flow",
      "x" : 724.0,
      "y" : 242.0
    }, {
      "name" : "quitters",
      "type" : "aux",
      "x" : 724.0,
      "y" : 261.0
    }, {
      "name" : "_0",
      "type" : "flow",
      "x" : 587.0,
      "y" : 175.0
    }, {
      "name" : "finishers",
      "type" : "aux",
      "x" : 621.0,
      "y" : 175.0
    }, {
      "name" : "percentage of passers",
      "type" : "aux",
      "x" : 694.0,
      "y" : 114.0
    }, {
      "name" : "satisfaction",
      "type" : "aux",
      "x" : 625.0,
      "y" : 310.0
    }, {
      "name" : "perceived quality of the teaching",
      "type" : "aux",
      "x" : 625.0,
      "y" : 374.0
    }, {
      "name" : "tuition fee",
      "type" : "aux",
      "x" : 437.0,
      "y" : 48.0
    }, {
      "name" : "former students",
      "type" : "aux",
      "x" : 586.0,
      "y" : 90.0
    }, {
      "name" : "former students and current students",
      "type" : "aux",
      "x" : 450.0,
      "y" : 140.0
    }, {
      "name" : "cost per student",
      "type" : "aux",
      "x" : 866.0,
      "y" : 68.0
    }, {
      "name" : "quality of the teaching",
      "type" : "aux",
      "x" : 791.0,
      "y" : 444.0
    }, {
      "name" : "experience",
      "type" : "aux",
      "x" : 403.0,
      "y" : 386.0
    }, {
      "name" : "expertise",
      "type" : "aux",
      "x" : 777.0,
      "y" : 514.0
    }, {
      "name" : "motivation",
      "type" : "aux",
      "x" : 986.0,
      "y" : 488.0
    }, {
      "name" : "workload",
      "type" : "aux",
      "x" : 760.0,
      "y" : 574.0
    }, {
      "name" : "complaints",
      "type" : "aux",
      "x" : 1036.0,
      "y" : 373.0
    }, {
      "name" : "perceived quality of the teaching in the previous period",
      "type" : "aux",
      "x" : 825.0,
      "y" : 348.0
    }, {
      "name" : "deterioration of the quality",
      "type" : "aux",
      "x" : 936.0,
      "y" : 257.0
    }, {
      "name" : "online students",
      "type" : "aux",
      "x" : 563.0,
      "y" : 538.0
    } ],
    "connectors" : [ {
      "from" : "5",
      "to" : "online students"
    }, {
      "from" : "5",
      "to" : "2"
    }, {
      "from" : "10",
      "to" : "7"
    }, {
      "from" : "10",
      "to" : "online students"
    }, {
      "from" : "13",
      "to" : "online students"
    }, {
      "from" : "online students",
      "to" : "finishers"
    }, {
      "from" : "percentage of passers",
      "to" : "finishers"
    }, {
      "from" : "online students",
      "to" : "quitters"
    }, {
      "from" : "satisfaction",
      "to" : "quitters"
    }, {
      "from" : "tuition fee",
      "to" : "_0"
    }, {
      "from" : "perceived quality of the teaching",
      "to" : "satisfaction"
    }, {
      "from" : "perceived quality of the teaching",
      "to" : "enrollments"
    }, {
      "from" : "_0",
      "to" : "former students"
    }, {
      "from" : "former students",
      "to" : "former students and current students"
    }, {
      "from" : "online students",
      "to" : "former students and current students"
    }, {
      "from" : "former students and current students",
      "to" : "_0"
    }, {
      "from" : "online students",
      "to" : "cost per student"
    }, {
      "from" : "workload",
      "to" : "motivation"
    }, {
      "from" : "complaints",
      "to" : "motivation"
    }, {
      "from" : "perceived quality of the teaching",
      "to" : "deterioration of the quality"
    }, {
      "from" : "perceived quality of the teaching in the previous period",
      "to" : "deterioration of the quality"
    }, {
      "from" : "deterioration of the quality",
      "to" : "cost per student"
    }, {
      "from" : "workload",
      "to" : "expertise"
    }, {
      "from" : "expertise",
      "to" : "quality of the teaching"
    }, {
      "from" : "motivation",
      "to" : "quality of the teaching"
    }, {
      "from" : "experience",
      "to" : "quality of the teaching"
    }, {
      "from" : "quality of the teaching",
      "to" : "perceived quality of the teaching"
    }, {
      "from" : "quality of the teaching",
      "to" : "perceived quality of the teaching in the previous period"
    }, {
      "from" : "deterioration of the quality",
      "to" : "complaints"
    }, {
      "from" : "former students and current students",
      "to" : "experience"
    }, {
      "from" : "cost per student",
      "to" : "tuition fee"
    }, {
      "from" : "online students",
      "to" : "workload"
    } ],
    "flowRoutes" : [ {
      "flowName" : "_0",
      "points" : [ [ 459.0, 232.0 ] ]
    }, {
      "flowName" : "_0",
      "points" : [ [ 724.0, 242.0 ] ]
    }, {
      "flowName" : "_0",
      "points" : [ [ 587.0, 175.0 ] ]
    } ]
  } ],
  "defaultSimulation" : {
    "timeStep" : "Year",
    "duration" : 16.0,
    "durationUnit" : "Year"
  },
  "metadata" : {
    "author" : "Dr. Erik Pruyt",
    "source" : "Pruyt, E., 2013. Small System Dynamics Models for Big Issues: Triple Jump towards Real-World Complexity. TU Delft Library. ISBN 978-94-6186-195-5",
    "license" : "CC-BY-NC-SA-4.0",
    "url" : "https://simulation.tudelft.nl/SD/"
  }
}